pysnpcall/__init__.py
pysnpcall/alignment.py
pysnpcall/checkSNPs.py
pysnpcall/filterSNPs.py
pysnpcall/getHQSNPs.py
pysnpcall/getINDELs.py
pysnpcall/intraClonalSNPs.py
pysnpcall/obtainSNPMatrix.py
pysnpcall/parse_vcf.py
pysnpcall/pySNPCallingPipeline.py
pysnpcall/read_config.py
pysnpcall/scinet_alignment.py
pysnpcall/utilities.py
pysnpcall/write_vcf.py
pySNPCall-0.1.dist-info/LICENSE.txt
pySNPCall-0.1.dist-info/METADATA
pySNPCall-0.1.dist-info/WHEEL
pySNPCall-0.1.dist-info/top_level.txt
pySNPCall-0.1.dist-info/RECORD
