Metadata-Version: 2.1
Name: pySNPCall
Version: 0.1
Summary: Python implementation of Java SNP calling pipeline (https://github.com/DSGlab/SNPCallingPipeline/)
Home-page: https://github.com/baribefe/pySNPCallingPipeline/
Author: Emmanuel Naziga
Author-email: baribefe@gmail.com
License: MIT
Platform: UNKNOWN
Requires-Dist: numpy
Requires-Dist: pandas
